z8ter/__init__.py
z8ter/config.py
z8ter/core.py
z8ter/errors.py
z8ter/logging_utils.py
z8ter/py.typed
z8ter/requests.py
z8ter/responses.py
z8ter/route_builders.py
z8ter/vite.py
z8ter/builders/__init__.py
z8ter/builders/app_builder.py
z8ter/builders/builder_functions.py
z8ter/builders/builder_step.py
z8ter/builders/helpers.py
z8ter/cli/__init__.py
z8ter/cli/create.py
z8ter/cli/main.py
z8ter/cli/new.py
z8ter/cli/run_server.py
z8ter/cli/scaffold_dev/create_project_template/main.py
z8ter/cli/scaffold_dev/create_project_template/endpoints/api/__init__.py
z8ter/cli/scaffold_dev/create_project_template/endpoints/api/hello.py
z8ter/cli/scaffold_dev/create_project_template/endpoints/views/__init__.py
z8ter/cli/scaffold_dev/create_project_template/endpoints/views/about.py
z8ter/cli/scaffold_dev/create_project_template/endpoints/views/index.py
z8ter/cli/scaffold_dev/create_project_template/views/__init__.py
z8ter/cli/scaffold_dev/create_project_template/views/about.py
z8ter/cli/scaffold_dev/create_project_template/views/index.py
z8ter/endpoints/__init__.py
z8ter/endpoints/api.py
z8ter/endpoints/helpers.py
z8ter/endpoints/view.py
z8ter/scaffold/create_api_template/api.py.j2
z8ter/scaffold/create_page_templates/base.jinja.j2
z8ter/scaffold/create_page_templates/page.jinja.j2
z8ter/scaffold/create_page_templates/page.ts.j2
z8ter/scaffold/create_page_templates/page.yaml.j2
z8ter/scaffold/create_page_templates/view.py.j2
z8ter/scaffold/create_project_template/.env
z8ter/scaffold/create_project_template/.flake8
z8ter/scaffold/create_project_template/.gitignore
z8ter/scaffold/create_project_template/LICENSE
z8ter/scaffold/create_project_template/README.md
z8ter/scaffold/create_project_template/main.py
z8ter/scaffold/create_project_template/package-lock.json
z8ter/scaffold/create_project_template/package.json
z8ter/scaffold/create_project_template/requirements.txt
z8ter/scaffold/create_project_template/tsconfig.json
z8ter/scaffold/create_project_template/vite.config.ts
z8ter-0.2.6.dist-info/licenses/LICENSE
z8ter-0.2.6.dist-info/METADATA
z8ter-0.2.6.dist-info/WHEEL
z8ter-0.2.6.dist-info/entry_points.txt
z8ter-0.2.6.dist-info/top_level.txt
z8ter-0.2.6.dist-info/RECORD
