Metadata-Version: 2.4
Name: z8ter
Version: 0.2.6
Summary: Lightweight full-stack async Python web framework built on Starlette designed for rapid development without compromising in UX
Author-email: Ashesh Nepal <nepalashesh8@gmail.com>
License: MIT License
Project-URL: Homepage, https://github.com/ashesh808/Z8ter
Project-URL: Issues, https://github.com/ashesh808/Z8ter/issues
Keywords: starlette,asgi,framework,uvicorn
Classifier: Programming Language :: Python :: 3
Classifier: Programming Language :: Python :: 3 :: Only
Classifier: Programming Language :: Python :: 3.10
Classifier: Programming Language :: Python :: 3.11
Classifier: Programming Language :: Python :: 3.12
Classifier: Programming Language :: Python :: 3.13
Classifier: Framework :: AsyncIO
Classifier: License :: OSI Approved :: MIT License
Classifier: Environment :: Console
Classifier: Intended Audience :: Developers
Requires-Python: >=3.10
License-File: LICENSE
Requires-Dist: starlette<1.0,>=0.36
Requires-Dist: jinja2<4,>=3.1
Requires-Dist: itsdangerous<3,>=2.1
Requires-Dist: uvicorn<1.0,>=0.30
Requires-Dist: rich<14,>=13.7
Provides-Extra: server
Requires-Dist: uvicorn[standard]<1.0,>=0.30; extra == "server"
Requires-Dist: rich<14,>=13.7; extra == "server"
Provides-Extra: dev
Requires-Dist: pytest; extra == "dev"
Requires-Dist: pytest-asyncio; extra == "dev"
Requires-Dist: ruff; extra == "dev"
Requires-Dist: mypy; extra == "dev"
Requires-Dist: build; extra == "dev"
Requires-Dist: twine; extra == "dev"
Provides-Extra: auth
Requires-Dist: z8ter-auth>=0.1.0; extra == "auth"
Dynamic: license-file
